LICENSE
README.md
setup.cfg
setup.py
src/restuml2code/__init__.py
src/restuml2code/__main__.py
src/restuml2code/item.py
src/restuml2code/main.py
src/restuml2code/puml.ebnf
src/restuml2code/restprocessor.py
src/restuml2code/uml.py
src/restuml2code/umldependencyscanner.py
src/restuml2code.egg-info/PKG-INFO
src/restuml2code.egg-info/SOURCES.txt
src/restuml2code.egg-info/dependency_links.txt
src/restuml2code.egg-info/entry_points.txt
src/restuml2code.egg-info/requires.txt
src/restuml2code.egg-info/top_level.txt